README.md
setup.py
ldap_simple_search/__init__.py
ldap_simple_search/search.py
ldap_simple_search.egg-info/PKG-INFO
ldap_simple_search.egg-info/SOURCES.txt
ldap_simple_search.egg-info/dependency_links.txt
ldap_simple_search.egg-info/not-zip-safe
ldap_simple_search.egg-info/requires.txt
ldap_simple_search.egg-info/top_level.txt