Metadata-Version: 1.0
Name: ldap-simple-search
Version: 0.1.2
Summary: Easily perform simple LDAP queries
Home-page: http://github.com/chaordic/python-ldap-simple-search
Author: Raphael P. Ribeiro
Author-email: raphael.ribeiro@chaordicsystems.com
License: GPL
Platform: UNKNOWN
